unityflow/__init__.py
unityflow/asset_resolver.py
unityflow/asset_tracker.py
unityflow/cli.py
unityflow/diff.py
unityflow/fast_parser.py
unityflow/formats.py
unityflow/git_utils.py
unityflow/hierarchy.py
unityflow/merge.py
unityflow/meta_generator.py
unityflow/normalizer.py
unityflow/parser.py
unityflow/query.py
unityflow/script_parser.py
unityflow/semantic_diff.py
unityflow/semantic_merge.py
unityflow/sprite.py
unityflow/validator.py
unityflow/animation/__init__.py
unityflow/animation/cli.py
unityflow/animation/models.py
unityflow/animation/mutate.py
unityflow/animation/parser.py
unityflow/animation/query.py
unityflow/animation/writer.py
unityflow/animator/__init__.py
unityflow/animator/cli.py
unityflow/animator/models.py
unityflow/animator/parser.py
unityflow/animator/query.py
unityflow/animator/writer.py
unityflow/data/__init__.py
unityflow/data/class_ids.json
unityflow-0.3.13.dist-info/licenses/LICENSE
unityflow-0.3.13.dist-info/METADATA
unityflow-0.3.13.dist-info/WHEEL
unityflow-0.3.13.dist-info/entry_points.txt
unityflow-0.3.13.dist-info/top_level.txt
unityflow-0.3.13.dist-info/RECORD
