Metadata-Version: 2.4
Name: unityflow
Version: 0.3.13
Summary: Unity workflow automation - edit, diff, and merge prefabs, scenes, and assets without the Unity Editor
Author: unityflow contributors
License: MIT
Project-URL: Homepage, https://github.com/TrueCyan/unityflow
Project-URL: Repository, https://github.com/TrueCyan/unityflow
Project-URL: Issues, https://github.com/TrueCyan/unityflow/issues
Keywords: unity,prefab,scene,asset,yaml,llm,workflow,automation,git
Classifier: Development Status :: 3 - Alpha
Classifier: Intended Audience :: Developers
Classifier: License :: OSI Approved :: MIT License
Classifier: Programming Language :: Python :: 3
Classifier: Programming Language :: Python :: 3.12
Classifier: Topic :: Software Development :: Version Control :: Git
Classifier: Topic :: Games/Entertainment
Requires-Python: >=3.12
License-File: LICENSE
Requires-Dist: unityparser>=4.0.0
Requires-Dist: rapidyaml>=0.10.0
Requires-Dist: click>=8.0.0
Requires-Dist: packaging>=21.0
Provides-Extra: dev
Requires-Dist: pytest~=9.0.0; extra == "dev"
Requires-Dist: pytest-cov~=6.0.0; extra == "dev"
Requires-Dist: black~=26.1.0; extra == "dev"
Requires-Dist: ruff~=0.14.0; extra == "dev"
Provides-Extra: all
Requires-Dist: unityflow[dev]; extra == "all"
Dynamic: license-file
